CHANGES.rst
MANIFEST.in
Makefile
README.rst
setup.py
version.txt
src/metapensiero/__init__.py
src/metapensiero.recipe.script.egg-info/PKG-INFO
src/metapensiero.recipe.script.egg-info/SOURCES.txt
src/metapensiero.recipe.script.egg-info/dependency_links.txt
src/metapensiero.recipe.script.egg-info/entry_points.txt
src/metapensiero.recipe.script.egg-info/namespace_packages.txt
src/metapensiero.recipe.script.egg-info/requires.txt
src/metapensiero.recipe.script.egg-info/top_level.txt
src/metapensiero/recipe/__init__.py
src/metapensiero/recipe/script/__init__.py
src/metapensiero/recipe/script/test.py
src/metapensiero/recipe/script/tests.rst