Metadata-Version: 1.1
Name: metapensiero.recipe.script
Version: 1.2
Summary: Buildout recipes to execute Python or Shell scripts
Home-page: https://bitbucket.org/lele/metapensiero.recipe.script
Author: Lele Gaifax
Author-email: lele@metapensiero.it
License: GPLv3+
Platform: UNKNOWN
Classifier: Programming Language :: Python
Classifier: Programming Language :: Python :: 2.7
Classifier: Programming Language :: Python :: 3.3
Classifier: License :: OSI Approved :: GNU General Public License v3 or later (GPLv3+)
Classifier: Framework :: Buildout
Classifier: Topic :: Software Development :: Build Tools
Classifier: Topic :: Software Development :: Libraries :: Python Modules
